{"UNK": 0, "讯": 1, "７": 2, "催": 3, "炭": 4, "蹶": 5, "晃": 6, "回": 7, "悟": 8, "遂": 9, "侄": 10, "琢": 11, "贤": 12, "脂": 13, "灶": 14, "欺": 15, "蝉": 16, "憔": 17, "具": 18, "跋": 19, "缪": 20, "违": 21, "窄": 22, "泰": 23, "刚": 24, "里": 25, "氛": 26, "蝶": 27, "耘": 28, "宛": 29, "長": 30, "敢": 31, "赢": 32, "惶": 33, "贺": 34, "栅": 35, "钼": 36, "臧": 37, "六": 38, "叉": 39, "溧": 40, "懦": 41, "匹": 42, "义": 43, "剂": 44, "跳": 45, "腱": 46, "膺": 47, "括": 48, "熱": 49, "廖": 50, "查": 51, "涅": 52, "腾": 53, "昂": 54, "姨": 55, "畈": 56, "囱": 57, "哪": 58, "全": 59, "民": 60, "奄": 61, "冉": 62, "弼": 63, "辛": 64, "~": 65, "腔": 66, "啸": 67, "～": 68, "氏": 69, "通": 70, "标": 71, "糟": 72, "喻": 73, "诱": 74, "秦": 75, "损": 76, "池": 77, "拔": 78, "爬": 79, "寧": 80, "渊": 81, "映": 82, "镰": 83, "缜": 84, "虽": 85, "童": 86, "庚": 87, "熄": 88, "洽": 89, "溺": 90, "婴": 91, "惯": 92, "栖": 93, "衫": 94, "戚": 95, "躺": 96, "软": 97, "凉": 98, "灾": 99, "碗": 100, "刻": 101, "凸": 102, "宫": 103, "拢": 104, "乳": 105, "邗": 106, "太": 107, "耻": 108, "喜": 109, "墙": 110, "册": 111, "啊": 112, "》": 113, "简": 114, "伞": 115, "渗": 116, "降": 117, "甲": 118, "乏": 119, "七": 120, "哨": 121, "剖": 122, "澄": 123, "敷": 124, "喧": 125, "甸": 126, "畏": 127, "撇": 128, "援": 129, "致": 130, "聘": 131, "佐": 132, "猖": 133, "過": 134, "押": 135, "逼": 136, "鞍": 137, "颊": 138, "秘": 139, "挡": 140, "（": 141, "鸟": 142, "拇": 143, "真": 144, "攻": 145, "时": 146, "肉": 147, "轧": 148, "临": 149, "锤": 150, "愧": 151, "哄": 152, "万": 153, "绕": 154, "严": 155, "师": 156, "卜": 157, "缓": 158, "隘": 159, "光": 160, "窝": 161, "拦": 162, "檬": 163, "曩": 164, "蓬": 165, "霸": 166, "俦": 167, "梗": 168, "煽": 169, "羊": 170, "衔": 171, "•": 172, "闲": 173, "嗅": 174, "沟": 175, "柿": 176, "免": 177, "季": 178, "储": 179, "锋": 180, "鍾": 181, "淤": 182, "J": 183, "窜": 184, "更": 185, "怖": 186, "衬": 187, "淀": 188, "泛": 189, "茁": 190, "腩": 191, "髋": 192, "绵": 193, "沾": 194, "划": 195, "雀": 196, "散": 197, "举": 198, "宿": 199, "搅": 200, "彭": 201, "熏": 202, "钜": 203, "潴": 204, "脚": 205, "售": 206, "凝": 207, "粤": 208, "乒": 209, "手": 210, "é": 211, "版": 212, "停": 213, "隋": 214, "瓯": 215, "洗": 216, "哼": 217, "剪": 218, "屏": 219, "崇": 220, "掏": 221, "炯": 222, "尝": 223, "铅": 224, "坐": 225, "漳": 226, "碴": 227, "褪": 228, "目": 229, "唱": 230, "逦": 231, "模": 232, "肾": 233, "朝": 234, "榻": 235, "需": 236, "蛰": 237, "柔": 238, "抒": 239, "增": 240, ")": 241, "骅": 242, "嬉": 243, "國": 244, "第": 245, "即": 246, "腐": 247, "琥": 248, "袖": 249, "d": 250, "了": 251, "羹": 252, "林": 253, "州": 254, "管": 255, "疴": 256, "斛": 257, "端": 258, "字": 259, "苓": 260, "廊": 261, "装": 262, "壳": 263, "涛": 264, "兑": 265, "十": 266, "昼": 267, "锁": 268, "俱": 269, "区": 270, "羁": 271, "悲": 272, "要": 273, "黄": 274, "谅": 275, "媒": 276, "戛": 277, "募": 278, "挥": 279, "挖": 280, "蜘": 281, "呢": 282, "寓": 283, "界": 284, "疃": 285, "采": 286, "酷": 287, "解": 288, "预": 289, "蚊": 290, "荼": 291, "粘": 292, "讶": 293, "烫": 294, "罪": 295, "娟": 296, "剽": 297, "入": 298, "档": 299, "谬": 300, "贿": 301, "茨": 302, "颉": 303, "脱": 304, "适": 305, "狸": 306, "赘": 307, "吻": 308, "昕": 309, "葱": 310, "镀": 311, "舰": 312, "北": 313, "吊": 314, "削": 315, "这": 316, "麂": 317, "鲸": 318, "驴": 319, "励": 320, "酿": 321, "扫": 322, "9": 323, "葬": 324, "攝": 325, "）": 326, "报": 327, "僻": 328, "巢": 329, "煤": 330, "嫩": 331, "拽": 332, "沃": 333, "痴": 334, "吆": 335, "佳": 336, "叠": 337, "获": 338, "怨": 339, "龚": 340, "劳": 341, "锦": 342, "莺": 343, "数": 344, "寂": 345, "硬": 346, "郑": 347, "喉": 348, "捐": 349, "宋": 350, "石": 351, "４": 352, "纭": 353, "际": 354, "捆": 355, "熬": 356, "楞": 357, "嬷": 358, "又": 359, "五": 360, "D": 361, "随": 362, "蚵": 363, "泻": 364, "_": 365, "斋": 366, "橄": 367, "兜": 368, "谱": 369, "狮": 370, "落": 371, "惹": 372, "墩": 373, "怆": 374, "笃": 375, "旬": 376, "淆": 377, "γ": 378, "申": 379, "新": 380, "颜": 381, "帕": 382, "军": 383, "寸": 384, "肋": 385, "弦": 386, "萎": 387, "颅": 388, "壶": 389, "绚": 390, "次": 391, "帮": 392, "导": 393, "π": 394, "躇": 395, "浪": 396, "贬": 397, "与": 398, "沉": 399, "曲": 400, "埔": 401, "蚕": 402, "濠": 403, "殡": 404, "薏": 405, "测": 406, "耀": 407, "籽": 408, "翁": 409, "栋": 410, "惮": 411, "序": 412, "１": 413, "偎": 414, "狂": 415, "强": 416, "惩": 417, "俟": 418, "众": 419, "知": 420, "婷": 421, "综": 422, "窥": 423, "淹": 424, "止": 425, "川": 426, "苛": 427, "霆": 428, "菊": 429, "刁": 430, "剥": 431, "蘸": 432, "逛": 433, "堃": 434, "词": 435, "侦": 436, "您": 437, "坠": 438, "牦": 439, "谲": 440, "媚": 441, "斟": 442, "斌": 443, "英": 444, "量": 445, "颓": 446, "玄": 447, "饭": 448, "熟": 449, "猩": 450, "９": 451, "＋": 452, "筛": 453, "廷": 454, "员": 455, "亿": 456, "三": 457, "律": 458, "阁": 459, "塌": 460, "沏": 461, "噪": 462, "统": 463, "扑": 464, "冠": 465, "基": 466, "沸": 467, "兀": 468, "染": 469, "捱": 470, "讽": 471, "泄": 472, "紧": 473, "盾": 474, "颇": 475, "逮": 476, "優": 477, "近": 478, "倪": 479, "烟": 480, "M": 481, "收": 482, "玉": 483, "徐": 484, "言": 485, "庭": 486, "悚": 487, "锻": 488, "息": 489, "苦": 490, "朔": 491, "匪": 492, "砍": 493, "戈": 494, "\t": 495, "航": 496, "娜": 497, "批": 498, "胞": 499, "流": 500, "款": 501, "潜": 502, "方": 503, "煎": 504, "肯": 505, "俗": 506, "哺": 507, "亥": 508, "嗡": 509, "帝": 510, "去": 511, "睿": 512, "禅": 513, "酣": 514, "握": 515, "醉": 516, "瞎": 517, "勿": 518, "进": 519, "找": 520, "处": 521, "授": 522, "脸": 523, "柱": 524, "纳": 525, "贼": 526, "悄": 527, "勘": 528, "颖": 529, "略": 530, "躬": 531, "。": 532, "眠": 533, "喽": 534, "塞": 535, "暂": 536, "种": 537, "庸": 538, "榨": 539, "节": 540, "濮": 541, "鹭": 542, "拼": 543, "赦": 544, "馈": 545, "幅": 546, "坦": 547, "漆": 548, "酱": 549, "邻": 550, "坂": 551, "休": 552, "长": 553, "寇": 554, "艺": 555, "咸": 556, "璨": 557, "没": 558, "翠": 559, "帽": 560, "帷": 561, "勤": 562, "缠": 563, "害": 564, "今": 565, "慌": 566, "癖": 567, "币": 568, "讹": 569, "镶": 570, "险": 571, "代": 572, "邓": 573, "易": 574, "延": 575, "索": 576, "抓": 577, "缘": 578, "鼎": 579, "干": 580, "符": 581, "纷": 582, "谤": 583, "痒": 584, "肌": 585, "茗": 586, "菡": 587, "趾": 588, "皙": 589, "满": 590, "焘": 591, "携": 592, "叶": 593, "卢": 594, "凡": 595, "捺": 596, "岩": 597, "饯": 598, "w": 599, "侈": 600, "蚀": 601, "大": 602, "陡": 603, "薪": 604, "桐": 605, "喱": 606, "琨": 607, "骞": 608, "淇": 609, "乍": 610, "室": 611, "驻": 612, "]": 613, "功": 614, "设": 615, "骐": 616, "渴": 617, "剃": 618, "商": 619, "把": 620, "峪": 621, "咏": 622, "零": 623, "蔓": 624, "饕": 625, "腮": 626, "尽": 627, "杈": 628, "贵": 629, "腭": 630, "旅": 631, "３": 632, "菌": 633, "寝": 634, "渐": 635, "灌": 636, "彬": 637, "嘟": 638, "束": 639, "江": 640, "舟": 641, "嫁": 642, "纪": 643, "聩": 644, "应": 645, "贮": 646, "债": 647, "纹": 648, "e": 649, "狐": 650, "半": 651, "老": 652, "份": 653, "磊": 654, "潞": 655, "唐": 656, "若": 657, "诵": 658, "段": 659, "专": 660, "娆": 661, "站": 662, "P": 663, "洛": 664, "官": 665, "域": 666, "垃": 667, "动": 668, "祁": 669, "砺": 670, "固": 671, "逗": 672, "终": 673, "瀚": 674, "竿": 675, "瞬": 676, "秒": 677, "稻": 678, "裹": 679, "衰": 680, "踪": 681, "经": 682, "勾": 683, "趴": 684, "完": 685, "扔": 686, "引": 687, "麻": 688, "沓": 689, "怪": 690, "菜": 691, "狠": 692, "挎": 693, "坛": 694, "剩": 695, "短": 696, "曼": 697, "偿": 698, "撤": 699, "q": 700, ".": 701, "昆": 702, "@": 703, "纱": 704, "嘘": 705, "妙": 706, "君": 707, "继": 708, "禧": 709, "按": 710, "叙": 711, "奎": 712, "弊": 713, "求": 714, "边": 715, "迤": 716, "救": 717, "末": 718, "澳": 719, "崎": 720, "堤": 721, "枞": 722, "虎": 723, "金": 724, "肚": 725, "吧": 726, "溶": 727, "魁": 728, "影": 729, "邕": 730, "车": 731, "遵": 732, "烂": 733, "洲": 734, "浓": 735, "棚": 736, "奶": 737, "獲": 738, "從": 739, "寨": 740, "恭": 741, "认": 742, "烽": 743, "坡": 744, "宵": 745, "耽": 746, "牲": 747, "凶": 748, "父": 749, "梯": 750, "渠": 751, "讨": 752, "踊": 753, "九": 754, "奏": 755, "勃": 756, "盎": 757, "牢": 758, "皎": 759, "顼": 760, "评": 761, "替": 762, "忘": 763, "晴": 764, "辗": 765, "锏": 766, "箱": 767, "棉": 768, "莳": 769, "樊": 770, "械": 771, "±": 772, "鹂": 773, "玺": 774, "悍": 775, "阎": 776, "卫": 777, "揪": 778, "叮": 779, "阱": 780, "U": 781, "姚": 782, "浙": 783, "虔": 784, "洋": 785, "仁": 786, "懋": 787, "遏": 788, "她": 789, "脉": 790, "香": 791, "而": 792, "記": 793, "\n": 794, "雨": 795, "它": 796, "垣": 797, "匀": 798, "值": 799, "支": 800, "枸": 801, "衢": 802, "及": 803, "政": 804, "程": 805, "A": 806, "宠": 807, "监": 808, "孝": 809, "溃": 810, "炫": 811, "魅": 812, "魚": 813, "煌": 814, "未": 815, "萄": 816, "训": 817, "样": 818, "部": 819, "秋": 820, "掩": 821, "嫖": 822, "仍": 823, "卉": 824, "迷": 825, "盏": 826, "阻": 827, "蓟": 828, "液": 829, "租": 830, "麟": 831, "蒂": 832, "嗜": 833, "畸": 834, "乘": 835, "抠": 836, "侮": 837, "N": 838, "果": 839, "奔": 840, "辟": 841, "凤": 842, "难": 843, "炒": 844, "彰": 845, "还": 846, "娴": 847, "股": 848, "茂": 849, "诟": 850, "就": 851, "旧": 852, "锰": 853, "迅": 854, "朵": 855, "渡": 856, "跷": 857, "銮": 858, "美": 859, "哲": 860, "遁": 861, "河": 862, "绪": 863, "峻": 864, "塑": 865, "秉": 866, "惧": 867, "思": 868, "篮": 869, "宏": 870, "呜": 871, "针": 872, "詹": 873, "遍": 874, "恼": 875, "务": 876, "窗": 877, "少": 878, "渤": 879, "多": 880, "尬": 881, "C": 882, "瓶": 883, "缆": 884, "缤": 885, "杯": 886, "黯": 887, "晒": 888, "洒": 889, "避": 890, "不": 891, "杞": 892, "粗": 893, "敛": 894, "走": 895, "欧": 896, "僚": 897, "蟒": 898, "再": 899, "虐": 900, "漱": 901, "届": 902, "足": 903, "茶": 904, "芦": 905, "厘": 906, "琛": 907, "舶": 908, "开": 909, "谍": 910, "绑": 911, "斓": 912, "姬": 913, "皋": 914, "坳": 915, "销": 916, "实": 917, "侵": 918, "掘": 919, "呆": 920, "剔": 921, "蒋": 922, "访": 923, "佛": 924, "绳": 925, "孕": 926, "収": 927, "潮": 928, "撬": 929, "■": 930, "鸿": 931, "浇": 932, "惟": 933, "韦": 934, "鸡": 935, "氰": 936, "T": 937, "趋": 938, "奥": 939, "　": 940, "兄": 941, "泪": 942, "乱": 943, "恰": 944, "舱": 945, "◆": 946, "泌": 947, "柯": 948, "峭": 949, "双": 950, "野": 951, "品": 952, "栈": 953, "嫣": 954, "在": 955, "唤": 956, "莞": 957, "盹": 958, "祀": 959, "忠": 960, "任": 961, "反": 962, "坤": 963, "你": 964, "蒯": 965, "备": 966, "赚": 967, "藤": 968, "岭": 969, "波": 970, "摸": 971, "鹰": 972, "验": 973, "谨": 974, "尘": 975, "啼": 976, "店": 977, "峙": 978, "频": 979, "斥": 980, "妖": 981, "追": 982, "柠": 983, "“": 984, "哟": 985, "p": 986, "阜": 987, "拍": 988, "贩": 989, "因": 990, "伸": 991, "舒": 992, "磬": 993, "坊": 994, "港": 995, "身": 996, "揽": 997, "l": 998, "恶": 999, "音": 1000, "加": 1001, "镇": 1002, "匆": 1003, "薇": 1004, "扮": 1005, "友": 1006, "歇": 1007, "吭": 1008, "豆": 1009, "白": 1010, "氨": 1011, "夷": 1012, "蹈": 1013, "溜": 1014, "骂": 1015, "额": 1016, "酵": 1017, "名": 1018, "逊": 1019, "洪": 1020, "斤": 1021, "丏": 1022, "僧": 1023, "碎": 1024, "祸": 1025, "瑾": 1026, "℃": 1027, "鬣": 1028, "兖": 1029, "菠": 1030, "嶂": 1031, "弈": 1032, "【": 1033, "感": 1034, "女": 1035, "疑": 1036, "编": 1037, "妈": 1038, "崔": 1039, "穴": 1040, "秩": 1041, "睦": 1042, "揉": 1043, "倩": 1044, "木": 1045, "尹": 1046, "猎": 1047, "医": 1048, "漫": 1049, "必": 1050, "炮": 1051, "对": 1052, "洱": 1053, "瑞": 1054, "み": 1055, "蓝": 1056, "护": 1057, "甩": 1058, "遇": 1059, "仗": 1060, "睁": 1061, "啻": 1062, "本": 1063, "雍": 1064, "橱": 1065, "乐": 1066, "瘦": 1067, "u": 1068, "胡": 1069, "苍": 1070, "屯": 1071, "缔": 1072, "享": 1073, "礁": 1074, "载": 1075, "袅": 1076, "齐": 1077, "瘫": 1078, "堆": 1079, "抛": 1080, "顶": 1081, "廣": 1082, "呼": 1083, "埃": 1084, "莹": 1085, "逝": 1086, "蝇": 1087, "偏": 1088, "房": 1089, "冢": 1090, "恐": 1091, "普": 1092, "愛": 1093, "列": 1094, "芯": 1095, "主": 1096, "莓": 1097, "守": 1098, "抨": 1099, "筋": 1100, "滢": 1101, "证": 1102, "项": 1103, "捉": 1104, "垫": 1105, "瞻": 1106, "抄": 1107, "璀": 1108, "爹": 1109, "胖": 1110, "歹": 1111, "噢": 1112, "丙": 1113, "叹": 1114, "措": 1115, "豫": 1116, "崛": 1117, "惕": 1118, "盼": 1119, "侪": 1120, "持": 1121, "岗": 1122, "筐": 1123, "媲": 1124, "奚": 1125, "冬": 1126, "茅": 1127, "业": 1128, "阀": 1129, "理": 1130, "兰": 1131, "哮": 1132, "队": 1133, "叛": 1134, "诗": 1135, "吞": 1136, "涎": 1137, "汹": 1138, "仨": 1139, "渝": 1140, "庙": 1141, "躲": 1142, "烹": 1143, "容": 1144, "嘀": 1145, "磋": 1146, "无": 1147, "算": 1148, "草": 1149, "幢": 1150, "肆": 1151, "淘": 1152, "醋": 1153, "期": 1154, "东": 1155, "榕": 1156, "呃": 1157, "诸": 1158, "见": 1159, "懒": 1160, "缢": 1161, "－": 1162, "例": 1163, "焦": 1164, "孵": 1165, "肥": 1166, "腊": 1167, "梅": 1168, "涯": 1169, "淮": 1170, "令": 1171, "学": 1172, "荟": 1173, "邵": 1174, "姆": 1175, "弱": 1176, "很": 1177, "至": 1178, "究": 1179, "贪": 1180, "祐": 1181, "挟": 1182, "矗": 1183, "捞": 1184, "仔": 1185, "盐": 1186, "伎": 1187, "撕": 1188, "博": 1189, "们": 1190, "驮": 1191, "拧": 1192, "闭": 1193, "贸": 1194, "岂": 1195, "攥": 1196, "尧": 1197, "袭": 1198, "探": 1199, "譬": 1200, "迫": 1201, "聆": 1202, "辽": 1203, "叨": 1204, "辜": 1205, "激": 1206, "秀": 1207, "怎": 1208, "溯": 1209, "0": 1210, "沧": 1211, "叩": 1212, "贫": 1213, "滴": 1214, "释": 1215, "！": 1216, "噜": 1217, "泊": 1218, "芝": 1219, "才": 1220, "待": 1221, "噩": 1222, "姊": 1223, "岖": 1224, "几": 1225, "送": 1226, "饥": 1227, "困": 1228, "起": 1229, "共": 1230, "酬": 1231, "肇": 1232, "雳": 1233, "氙": 1234, "弄": 1235, "么": 1236, "层": 1237, "澡": 1238, "蔗": 1239, "月": 1240, "亏": 1241, "畅": 1242, "匣": 1243, "厚": 1244, "顾": 1245, "谆": 1246, "家": 1247, "咨": 1248, "h": 1249, "霄": 1250, "传": 1251, "匝": 1252, "牙": 1253, "用": 1254, "媛": 1255, "亢": 1256, "准": 1257, "菇": 1258, "审": 1259, "唠": 1260, "武": 1261, "盒": 1262, "恩": 1263, "瞄": 1264, "溪": 1265, "炉": 1266, "净": 1267, "异": 1268, "乎": 1269, "县": 1270, "殂": 1271, "狼": 1272, "缮": 1273, "驿": 1274, "刹": 1275, "瑕": 1276, "丧": 1277, "奠": 1278, "纲": 1279, "岷": 1280, "红": 1281, "o": 1282, "该": 1283, "滚": 1284, "荤": 1285, "咤": 1286, "刮": 1287, "服": 1288, "衷": 1289, "槟": 1290, "绋": 1291, "岔": 1292, "青": 1293, "笼": 1294, "职": 1295, "问": 1296, "刺": 1297, "农": 1298, "厅": 1299, "疾": 1300, "鞭": 1301, "藐": 1302, "囊": 1303, "厂": 1304, "矩": 1305, "娥": 1306, "礓": 1307, "郸": 1308, "蛙": 1309, "镳": 1310, "腿": 1311, "摆": 1312, "捏": 1313, "坍": 1314, "裘": 1315, "侍": 1316, "捅": 1317, "龟": 1318, "沦": 1319, "窿": 1320, "券": 1321, "侗": 1322, "糖": 1323, "康": 1324, "娄": 1325, "遣": 1326, "村": 1327, "b": 1328, "悦": 1329, "烘": 1330, "毕": 1331, "偶": 1332, "闵": 1333, "肘": 1334, "睹": 1335, "跸": 1336, "劣": 1337, "献": 1338, "诈": 1339, "汪": 1340, "炸": 1341, "4": 1342, "图": 1343, "馨": 1344, "觑": 1345, "霜": 1346, "淋": 1347, "郡": 1348, "橙": 1349, "敞": 1350, "亳": 1351, "犷": 1352, "陈": 1353, "竟": 1354, "钮": 1355, "深": 1356, "页": 1357, "泵": 1358, "机": 1359, "垂": 1360, "g": 1361, "云": 1362, "撼": 1363, "淡": 1364, "雕": 1365, "剿": 1366, "郊": 1367, "穗": 1368, "冕": 1369, "欄": 1370, "场": 1371, "爆": 1372, "慢": 1373, "钙": 1374, "鉴": 1375, "蓓": 1376, "裁": 1377, "属": 1378, "苑": 1379, "码": 1380, "明": 1381, "浒": 1382, "扳": 1383, "绣": 1384, "捧": 1385, "汰": 1386, "运": 1387, "夜": 1388, "慧": 1389, "甫": 1390, "仲": 1391, "岚": 1392, "母": 1393, "蓉": 1394, "％": 1395, "绷": 1396, "】": 1397, "寡": 1398, "优": 1399, "湾": 1400, "呀": 1401, "亡": 1402, "屈": 1403, "穷": 1404, "蝙": 1405, "且": 1406, "苗": 1407, "弘": 1408, "闻": 1409, "儒": 1410, "聚": 1411, "轨": 1412, "梦": 1413, "擅": 1414, "血": 1415, "读": 1416, "源": 1417, "圆": 1418, "绎": 1419, "欢": 1420, "袜": 1421, "薛": 1422, "埂": 1423, "添": 1424, "霓": 1425, "喔": 1426, "為": 1427, "=": 1428, "弃": 1429, "刊": 1430, "工": 1431, "戴": 1432, "绸": 1433, "掳": 1434, "舵": 1435, "岁": 1436, "雇": 1437, "瑟": 1438, "地": 1439, "当": 1440, "贝": 1441, "庶": 1442, "雷": 1443, "受": 1444, "缄": 1445, "鬼": 1446, "釉": 1447, "善": 1448, "卑": 1449, "亩": 1450, "漠": 1451, "斐": 1452, "幂": 1453, "谢": 1454, "蜒": 1455, "卧": 1456, "曹": 1457, "勉": 1458, "泥": 1459, "腻": 1460, "岛": 1461, "歌": 1462, "勋": 1463, "换": 1464, "玛": 1465, "臻": 1466, "篷": 1467, "寒": 1468, "棱": 1469, "归": 1470, "架": 1471, "材": 1472, "痛": 1473, "况": 1474, "S": 1475, "劝": 1476, "娶": 1477, "嗲": 1478, "膦": 1479, "盖": 1480, "ù": 1481, "睡": 1482, "愈": 1483, "述": 1484, "附": 1485, "巧": 1486, "觉": 1487, "龄": 1488, "筹": 1489, "忆": 1490, "廉": 1491, "胃": 1492, "帅": 1493, "骄": 1494, "毯": 1495, "文": 1496, "敌": 1497, "骚": 1498, "蛾": 1499, "娑": 1500, "唇": 1501, "癣": 1502, "拂": 1503, "屠": 1504, "匠": 1505, " ": 1506, "裙": 1507, "枝": 1508, "飓": 1509, "阐": 1510, "阿": 1511, "力": 1512, "棋": 1513, "仪": 1514, "瓷": 1515, "甜": 1516, "稽": 1517, "骤": 1518, "寅": 1519, "邢": 1520, "檐": 1521, "作": 1522, "造": 1523, "湍": 1524, "公": 1525, "Q": 1526, "斩": 1527, "；": 1528, "薦": 1529, "亮": 1530, "弗": 1531, "子": 1532, "笨": 1533, "洁": 1534, "驱": 1535, "抹": 1536, "跪": 1537, "狗": 1538, "铎": 1539, "尾": 1540, "禽": 1541, "迥": 1542, "肮": 1543, "酡": 1544, "扛": 1545, "圃": 1546, "夯": 1547, "科": 1548, "黑": 1549, "已": 1550, "燕": 1551, "皓": 1552, "杓": 1553, "跆": 1554, "颂": 1555, "扼": 1556, "ず": 1557, "陷": 1558, "矶": 1559, "肩": 1560, "蕾": 1561, "安": 1562, "尼": 1563, "网": 1564, "晕": 1565, "辉": 1566, "碌": 1567, "询": 1568, "炜": 1569, "缭": 1570, "检": 1571, "笙": 1572, "存": 1573, "板": 1574, "咧": 1575, "誓": 1576, "巷": 1577, "歧": 1578, "绽": 1579, "拥": 1580, "术": 1581, "葛": 1582, "缨": 1583, "察": 1584, "Y": 1585, "圭": 1586, "伴": 1587, "舅": 1588, "戏": 1589, "账": 1590, "磁": 1591, "宝": 1592, "5": 1593, "髦": 1594, "鑫": 1595, "铲": 1596, "瑰": 1597, "瓜": 1598, "疆": 1599, "甘": 1600, "皱": 1601, "松": 1602, "刷": 1603, "挽": 1604, "过": 1605, "`": 1606, "灭": 1607, "锂": 1608, "辨": 1609, "命": 1610, "佟": 1611, "犬": 1612, "群": 1613, "袁": 1614, "裕": 1615, "煊": 1616, "风": 1617, "亲": 1618, "湖": 1619, "肤": 1620, "拄": 1621, "均": 1622, "遭": 1623, "孔": 1624, "暮": 1625, "黏": 1626, "俺": 1627, "泼": 1628, "擎": 1629, "结": 1630, "杰": 1631, "熨": 1632, "讼": 1633, "斑": 1634, "头": 1635, "分": 1636, "混": 1637, "议": 1638, "渍": 1639, "姐": 1640, "聪": 1641, "藩": 1642, "糊": 1643, "稍": 1644, "织": 1645, "篆": 1646, "崩": 1647, "旷": 1648, "瞿": 1649, "诚": 1650, "静": 1651, "佚": 1652, "兹": 1653, "驭": 1654, "弧": 1655, "餮": 1656, "粉": 1657, "芒": 1658, "偌": 1659, "赃": 1660, "胀": 1661, "够": 1662, "娘": 1663, "永": 1664, "佑": 1665, "答": 1666, "皇": 1667, "荐": 1668, "市": 1669, "跨": 1670, "漂": 1671, "诊": 1672, "棠": 1673, "食": 1674, "—": 1675, "涌": 1676, "土": 1677, "攀": 1678, "隽": 1679, "益": 1680, "楠": 1681, "径": 1682, "壑": 1683, "唯": 1684, "罩": 1685, "蝠": 1686, "掺": 1687, "历": 1688, "儡": 1689, "镐": 1690, "捍": 1691, "升": 1692, "八": 1693, "拘": 1694, "拳": 1695, "骋": 1696, "啥": 1697, "笑": 1698, "联": 1699, "杂": 1700, "靳": 1701, "错": 1702, "计": 1703, "奋": 1704, "衣": 1705, "黝": 1706, "幽": 1707, "漓": 1708, "褚": 1709, "畴": 1710, "缉": 1711, "妄": 1712, "故": 1713, "燃": 1714, "迁": 1715, "控": 1716, "允": 1717, "&": 1718, "羞": 1719, "绮": 1720, "滞": 1721, "翟": 1722, "执": 1723, "璃": 1724, "幻": 1725, "兔": 1726, "下": 1727, "递": 1728, "袍": 1729, "启": 1730, "寺": 1731, "蝴": 1732, "逾": 1733, "琪": 1734, "刽": 1735, "璧": 1736, "懈": 1737, "叱": 1738, "资": 1739, "禁": 1740, "虾": 1741, "、": 1742, "伺": 1743, "瞪": 1744, "余": 1745, "句": 1746, "梁": 1747, "邦": 1748, "庇": 1749, "骗": 1750, "巫": 1751, "芽": 1752, "尴": 1753, "痘": 1754, "酩": 1755, "挂": 1756, "象": 1757, "默": 1758, "妮": 1759, "n": 1760, "倍": 1761, "嚎": 1762, "著": 1763, "右": 1764, "膏": 1765, "羽": 1766, "嘻": 1767, "疚": 1768, "澎": 1769, "菁": 1770, "题": 1771, "膨": 1772, "听": 1773, "团": 1774, "宾": 1775, "耶": 1776, "借": 1777, "燥": 1778, "獾": 1779, "鼻": 1780, "彤": 1781, "咎": 1782, "凋": 1783, "臂": 1784, "厌": 1785, "改": 1786, "识": 1787, "歪": 1788, "择": 1789, "鹤": 1790, "[": 1791, "废": 1792, "秽": 1793, "势": 1794, "阵": 1795, "倡": 1796, "赡": 1797, "试": 1798, "治": 1799, "铁": 1800, "否": 1801, "锹": 1802, "狱": 1803, "搓": 1804, "笔": 1805, "醛": 1806, "蔡": 1807, "焜": 1808, "沐": 1809, "叭": 1810, "妞": 1811, "巡": 1812, "压": 1813, "逃": 1814, "棕": 1815, "猛": 1816, "派": 1817, "恣": 1818, "骁": 1819, "嘲": 1820, "藏": 1821, "画": 1822, "吗": 1823, "辖": 1824, "既": 1825, "葡": 1826, "跃": 1827, "竖": 1828, "尖": 1829, "婆": 1830, "吾": 1831, "警": 1832, "陆": 1833, "蚩": 1834, "迩": 1835, "枉": 1836, "莆": 1837, "族": 1838, "「": 1839, "肠": 1840, "摩": 1841, "邸": 1842, "向": 1843, "斧": 1844, "堡": 1845, "私": 1846, "平": 1847, "链": 1848, "掌": 1849, "制": 1850, "每": 1851, "盘": 1852, "6": 1853, "酸": 1854, "桩": 1855, "觅": 1856, "郎": 1857, "寿": 1858, "饼": 1859, "枚": 1860, "除": 1861, "局": 1862, "神": 1863, "缅": 1864, "苹": 1865, "陳": 1866, "庆": 1867, "候": 1868, "根": 1869, "书": 1870, "皖": 1871, "攒": 1872, "礼": 1873, "膝": 1874, "拿": 1875, "1": 1876, "伯": 1877, "非": 1878, "址": 1879, "闪": 1880, "溴": 1881, "乓": 1882, "刀": 1883, "朽": 1884, " ": 1885, "哈": 1886, "卦": 1887, "键": 1888, "背": 1889, "枭": 1890, "尿": 1891, "妨": 1892, "最": 1893, "诙": 1894, "亚": 1895, "歼": 1896, "艮": 1897, "荒": 1898, "哉": 1899, "茯": 1900, "颁": 1901, "蘑": 1902, "睛": 1903, "犀": 1904, "霾": 1905, "正": 1906, "蹬": 1907, "街": 1908, "岱": 1909, "浴": 1910, "瞧": 1911, "总": 1912, "艳": 1913, "印": 1914, "選": 1915, "坟": 1916, "西": 1917, "状": 1918, "恍": 1919, "课": 1920, "爽": 1921, "骆": 1922, "”": 1923, "+": 1924, "靴": 1925, "□": 1926, "钥": 1927, "可": 1928, "硫": 1929, "惬": 1930, "并": 1931, "寻": 1932, "幕": 1933, "骨": 1934, "忿": 1935, "蹄": 1936, "铝": 1937, "犊": 1938, "境": 1939, "潦": 1940, "佼": 1941, "票": 1942, "各": 1943, "润": 1944, "疫": 1945, "绍": 1946, "帖": 1947, "聂": 1948, "俞": 1949, "体": 1950, "越": 1951, "#": 1952, "剧": 1953, "赞": 1954, "挤": 1955, "竭": 1956, "扬": 1957, "船": 1958, "酯": 1959, "喊": 1960, "忧": 1961, "抢": 1962, "'": 1963, "Z": 1964, "构": 1965, "晤": 1966, "闯": 1967, "嫌": 1968, "拷": 1969, "辑": 1970, "席": 1971, "鹏": 1972, "征": 1973, "淑": 1974, "裤": 1975, "张": 1976, "党": 1977, "伍": 1978, "锄": 1979, "喃": 1980, "托": 1981, "抗": 1982, "敏": 1983, "懵": 1984, "助": 1985, "疲": 1986, "吓": 1987, "昨": 1988, "哥": 1989, "娇": 1990, "格": 1991, "响": 1992, "抱": 1993, "颐": 1994, "井": 1995, "策": 1996, "桥": 1997, "仅": 1998, "扩": 1999, "逵": 2000, "佣": 2001, "湃": 2002, "行": 2003, "屿": 2004, "率": 2005, "闆": 2006, "疮": 2007, "舉": 2008, "南": 2009, "昏": 2010, "柜": 2011, "串": 2012, "烩": 2013, "刘": 2014, "驶": 2015, "馍": 2016, "人": 2017, "前": 2018, "涡": 2019, "络": 2020, "椅": 2021, "鸶": 2022, "砀": 2023, "廿": 2024, "飙": 2025, "笠": 2026, "杏": 2027, "录": 2028, "诽": 2029, "莘": 2030, "雾": 2031, "昧": 2032, "珊": 2033, "仑": 2034, "闽": 2035, "男": 2036, "素": 2037, "慶": 2038, "匍": 2039, "初": 2040, "堰": 2041, "脖": 2042, "玩": 2043, "有": 2044, "谦": 2045, "案": 2046, "二": 2047, "荡": 2048, "茄": 2049, "呈": 2050, "撒": 2051, "为": 2052, "函": 2053, "射": 2054, "蕴": 2055, "骑": 2056, "筑": 2057, "件": 2058, "趟": 2059, "衡": 2060, "凳": 2061, "壮": 2062, "肝": 2063, "傲": 2064, "讷": 2065, "岙": 2066, "秤": 2067, "L": 2068, "菲": 2069, "厝": 2070, "碟": 2071, "浑": 2072, "威": 2073, "ほ": 2074, "／": 2075, "招": 2076, "巴": 2077, "饷": 2078, "婶": 2079, "贻": 2080, "唷": 2081, "何": 2082, "莉": 2083, "聊": 2084, "交": 2085, "成": 2086, "煲": 2087, "尔": 2088, "坝": 2089, "味": 2090, "上": 2091, "眷": 2092, "荧": 2093, "珏": 2094, "瘤": 2095, "泽": 2096, "邱": 2097, "捎": 2098, "烦": 2099, "看": 2100, "卸": 2101, "項": 2102, "氓": 2103, "B": 2104, "比": 2105, "搜": 2106, "签": 2107, "硅": 2108, "醒": 2109, "厢": 2110, "温": 2111, "拜": 2112, "袤": 2113, "拣": 2114, "片": 2115, "抬": 2116, "２": 2117, "稳": 2118, "写": 2119, "达": 2120, "砂": 2121, "吹": 2122, "栗": 2123, "②": 2124, "卡": 2125, "拒": 2126, "央": 2127, "來": 2128, "百": 2129, "线": 2130, "耕": 2131, "胤": 2132, "冶": 2133, "淌": 2134, "怂": 2135, "窖": 2136, "冷": 2137, "埠": 2138, "华": 2139, "顿": 2140, "偷": 2141, "贯": 2142, "芜": 2143, "掉": 2144, "婚": 2145, "丹": 2146, "叫": 2147, "烤": 2148, "滇": 2149, "靡": 2150, "竹": 2151, "罐": 2152, "夕": 2153, "夸": 2154, "戟": 2155, "千": 2156, "a": 2157, "急": 2158, "介": 2159, "费": 2160, "內": 2161, "钵": 2162, "盆": 2163, "塔": 2164, "肃": 2165, "挠": 2166, "直": 2167, "馆": 2168, "班": 2169, "事": 2170, "r": 2171, "让": 2172, "晓": 2173, "间": 2174, "说": 2175, "姿": 2176, "乞": 2177, "此": 2178, "罚": 2179, "癌": 2180, "臃": 2181, "放": 2182, "铠": 2183, "袱": 2184, "・": 2185, "扣": 2186, "妹": 2187, "忽": 2188, "魏": 2189, "奕": 2190, "鹅": 2191, "乔": 2192, "垮": 2193, "镑": 2194, "论": 2195, "忏": 2196, "示": 2197, "撰": 2198, "禾": 2199, "倭": 2200, "带": 2201, "洞": 2202, "徽": 2203, "術": 2204, "社": 2205, "暴": 2206, "讧": 2207, "门": 2208, "酌": 2209, "歙": 2210, "怔": 2211, "谈": 2212, "琴": 2213, "顽": 2214, "登": 2215, "莎": 2216, "撞": 2217, "敬": 2218, "饬": 2219, "欠": 2220, "忌": 2221, "卿": 2222, "核": 2223, "循": 2224, "沫": 2225, "颠": 2226, "飞": 2227, "恋": 2228, "俯": 2229, "些": 2230, "韩": 2231, "领": 2232, "踮": 2233, "谧": 2234, "柏": 2235, "植": 2236, "蛇": 2237, "症": 2238, "蛀": 2239, "G": 2240, "弟": 2241, "颤": 2242, "缝": 2243, "园": 2244, "杖": 2245, "雅": 2246, "判": 2247, "灿": 2248, "铐": 2249, "雹": 2250, "浅": 2251, "球": 2252, "琦": 2253, "冯": 2254, "吐": 2255, "兢": 2256, "耳": 2257, "脾": 2258, "垄": 2259, "税": 2260, "轮": 2261, "葫": 2262, "菱": 2263, "螃": 2264, "晚": 2265, "仰": 2266, "樵": 2267, "泡": 2268, "珀": 2269, "\\": 2270, "è": 2271, "差": 2272, "浩": 2273, "憧": 2274, "奈": 2275, "夭": 2276, "革": 2277, "愣": 2278, "辞": 2279, "污": 2280, "冀": 2281, "辇": 2282, "纠": 2283, "帘": 2284, "做": 2285, "肪": 2286, "保": 2287, "养": 2288, "钻": 2289, "台": 2290, "绅": 2291, "辙": 2292, "婿": 2293, "热": 2294, "剑": 2295, "啪": 2296, "罗": 2297, "捡": 2298, "腰": 2299, "内": 2300, "伤": 2301, "树": 2302, "吨": 2303, "酗": 2304, "茹": 2305, "靖": 2306, "便": 2307, "像": 2308, "米": 2309, "称": 2310, "配": 2311, "虚": 2312, "吃": 2313, "熊": 2314, "憾": 2315, "争": 2316, "巨": 2317, "惑": 2318, "濒": 2319, "广": 2320, "摄": 2321, "破": 2322, "…": 2323, "删": 2324, "佩": 2325, "表": 2326, "凑": 2327, "磅": 2328, "鲜": 2329, "桂": 2330, "庐": 2331, "砝": 2332, "坚": 2333, "毋": 2334, "後": 2335, "餐": 2336, "舜": 2337, "吸": 2338, "驳": 2339, "蜷": 2340, "蹴": 2341, "６": 2342, "扒": 2343, "陀": 2344, "鳄": 2345, "生": 2346, "O": 2347, "袋": 2348, "迈": 2349, "逆": 2350, "卤": 2351, "化": 2352, "独": 2353, "挪": 2354, "陨": 2355, "徊": 2356, "悠": 2357, "范": 2358, "髓": 2359, "祚": 2360, "焕": 2361, "惚": 2362, "奸": 2363, "滋": 2364, "调": 2365, "花": 2366, "鲁": 2367, "性": 2368, "氧": 2369, "晶": 2370, "摇": 2371, "筲": 2372, "簿": 2373, "橡": 2374, "焊": 2375, "祺": 2376, "谜": 2377, "嶝": 2378, "曙": 2379, "旭": 2380, "御": 2381, "毛": 2382, "-": 2383, "闫": 2384, "离": 2385, "厕": 2386, "晔": 2387, "坪": 2388, "翘": 2389, "浏": 2390, "甄": 2391, "痕": 2392, "龙": 2393, "决": 2394, "吕": 2395, "诀": 2396, "哑": 2397, "惭": 2398, "『": 2399, "纽": 2400, "茜": 2401, "由": 2402, "谋": 2403, "吮": 2404, "鸵": 2405, "樟": 2406, "潘": 2407, "搞": 2408, "夺": 2409, "敲": 2410, "?": 2411, "歆": 2412, "拚": 2413, "晖": 2414, "巾": 2415, "诺": 2416, "弓": 2417, "拎": 2418, "噬": 2419, "左": 2420, "枯": 2421, "屋": 2422, "形": 2423, "祥": 2424, "豪": 2425, "研": 2426, "砸": 2427, "宰": 2428, "墟": 2429, "凭": 2430, "嘶": 2431, "憎": 2432, "辐": 2433, "糕": 2434, "琼": 2435, "芳": 2436, "凄": 2437, "尉": 2438, "田": 2439, "豁": 2440, "情": 2441, "诠": 2442, "儿": 2443, "醇": 2444, "滑": 2445, "缴": 2446, "﹑": 2447, "挫": 2448, "环": 2449, "累": 2450, "钉": 2451, "佔": 2452, "．": 2453, "镯": 2454, "类": 2455, "超": 2456, "价": 2457, "绩": 2458, "斗": 2459, "练": 2460, "敖": 2461, "皮": 2462, "框": 2463, "颗": 2464, "屑": 2465, "黔": 2466, "蜕": 2467, "碍": 2468, "雏": 2469, "夹": 2470, "畔": 2471, "什": 2472, "穹": 2473, "珉": 2474, "娅": 2475, "丁": 2476, "郭": 2477, "则": 2478, "宴": 2479, "接": 2480, "矛": 2481, "喘": 2482, "膘": 2483, "疗": 2484, "法": 2485, "滨": 2486, "绝": 2487, "抚": 2488, "抖": 2489, "心": 2490, "胶": 2491, "会": 2492, "景": 2493, "俏": 2494, "省": 2495, "姗": 2496, "愉": 2497, "桃": 2498, "钢": 2499, "兽": 2500, "仓": 2501, "孟": 2502, "汤": 2503, "却": 2504, "盲": 2505, "粒": 2506, "碰": 2507, "促": 2508, "栽": 2509, "截": 2510, "整": 2511, "鸣": 2512, "津": 2513, "隧": 2514, "滤": 2515, "隐": 2516, "逻": 2517, "硕": 2518, "f": 2519, "斜": 2520, "匿": 2521, "密": 2522, "绒": 2523, "踢": 2524, "寮": 2525, "V": 2526, "财": 2527, "聋": 2528, "鱼": 2529, "籍": 2530, "灰": 2531, "葺": 2532, "绢": 2533, "侧": 2534, "亟": 2535, "牺": 2536, "牵": 2537, "路": 2538, "得": 2539, "|": 2540, "陕": 2541, "含": 2542, "鳞": 2543, "铭": 2544, "埋": 2545, "倾": 2546, "利": 2547, "谊": 2548, "梢": 2549, "漩": 2550, "彪": 2551, "和": 2552, "往": 2553, "空": 2554, "孙": 2555, "糅": 2556, "荫": 2557, "嬴": 2558, "沪": 2559, "级": 2560, ":": 2561, "痊": 2562, "炊": 2563, "炎": 2564, "积": 2565, "披": 2566, "墨": 2567, "灯": 2568, "鄧": 2569, "镂": 2570, "常": 2571, "欣": 2572, "耿": 2573, "戡": 2574, ",": 2575, "推": 2576, "暗": 2577, "黎": 2578, "禄": 2579, "钞": 2580, "葵": 2581, "麦": 2582, "搏": 2583, "货": 2584, "着": 2585, "萃": 2586, "愤": 2587, "建": 2588, "尤": 2589, "猷": 2590, "集": 2591, "汁": 2592, "卖": 2593, "锣": 2594, "铺": 2595, "绥": 2596, "殊": 2597, "憬": 2598, "澜": 2599, "蛋": 2600, "输": 2601, "纺": 2602, "赋": 2603, "珠": 2604, "捣": 2605, "鄞": 2606, "琅": 2607, "Ⅰ": 2608, "注": 2609, "己": 2610, "摊": 2611, "另": 2612, "器": 2613, "粽": 2614, "纵": 2615, "出": 2616, "钩": 2617, "峡": 2618, "噱": 2619, "世": 2620, "马": 2621, "踵": 2622, "阅": 2623, "糯": 2624, "阴": 2625, "猪": 2626, "伽": 2627, "躯": 2628, "京": 2629, "坞": 2630, "割": 2631, "估": 2632, "棒": 2633, "慑": 2634, "荷": 2635, "圳": 2636, "信": 2637, "修": 2638, "劫": 2639, "瞥": 2640, "嘴": 2641, "蜡": 2642, "逍": 2643, "馅": 2644, "R": 2645, "疏": 2646, "浊": 2647, "恳": 2648, "焚": 2649, "驺": 2650, "薄": 2651, "意": 2652, "粪": 2653, "K": 2654, "係": 2655, "俊": 2656, "贷": 2657, "霍": 2658, "铂": 2659, "败": 2660, "冈": 2661, "暇": 2662, "厄": 2663, "育": 2664, "触": 2665, "’": 2666, "尊": 2667, "躁": 2668, "峥": 2669, "烁": 2670, "施": 2671, "捂": 2672, "拉": 2673, "谎": 2674, "原": 2675, "抵": 2676, "客": 2677, "疯": 2678, "琐": 2679, "梨": 2680, "速": 2681, "吠": 2682, "鮮": 2683, "冒": 2684, "糙": 2685, "÷": 2686, "语": 2687, "筒": 2688, "膀": 2689, "罘": 2690, "技": 2691, "振": 2692, "矿": 2693, "壁": 2694, "饲": 2695, "翻": 2696, "稚": 2697, "谭": 2698, "夫": 2699, "獗": 2700, "良": 2701, "褐": 2702, "扶": 2703, "咬": 2704, "来": 2705, "役": 2706, "屁": 2707, "歷": 2708, "溢": 2709, "酥": 2710, "呐": 2711, "汝": 2712, "翔": 2713, "愿": 2714, "枣": 2715, "辱": 2716, "闷": 2717, "玫": 2718, "镁": 2719, "兼": 2720, "恬": 2721, "虞": 2722, "窑": 2723, "玻": 2724, "山": 2725, "企": 2726, "圣": 2727, "郅": 2728, "扎": 2729, "狭": 2730, "搡": 2731, "甚": 2732, "盗": 2733, "高": 2734, "萝": 2735, "宇": 2736, "暖": 2737, "灵": 2738, "帆": 2739, "搭": 2740, "愁": 2741, "沙": 2742, "智": 2743, "嵴": 2744, "减": 2745, "吉": 2746, "蜜": 2747, "舌": 2748, "蒸": 2749, "者": 2750, "希": 2751, "慰": 2752, "鄂": 2753, "锐": 2754, "绘": 2755, "库": 2756, "邮": 2757, "之": 2758, "铬": 2759, "围": 2760, "胎": 2761, "窍": 2762, "宁": 2763, "弥": 2764, "屹": 2765, "垦": 2766, "缀": 2767, "负": 2768, "豢": 2769, "物": 2770, "梆": 2771, "肺": 2772, "奇": 2773, "蜿": 2774, "3": 2775, "莲": 2776, "刃": 2777, "浮": 2778, "践": 2779, "谀": 2780, "扯": 2781, "凯": 2782, "靠": 2783, "兴": 2784, "昱": 2785, "活": 2786, "芸": 2787, "午": 2788, "滩": 2789, "变": 2790, "卓": 2791, "贴": 2792, "退": 2793, "』": 2794, "擒": 2795, "精": 2796, "挨": 2797, "斯": 2798, "跻": 2799, "咐": 2800, "耐": 2801, "摔": 2802, "？": 2803, "障": 2804, "融": 2805, "殓": 2806, "色": 2807, "娃": 2808, "小": 2809, "士": 2810, "瘾": 2811, "志": 2812, "姓": 2813, "勒": 2814, "迟": 2815, "营": 2816, "祝": 2817, "沈": 2818, "棺": 2819, "旺": 2820, "涨": 2821, "轼": 2822, "到": 2823, "番": 2824, "杀": 2825, "眉": 2826, "圾": 2827, "早": 2828, "约": 2829, "跌": 2830, "赠": 2831, "箫": 2832, "彻": 2833, "c": 2834, "包": 2835, "塘": 2836, "殷": 2837, "霉": 2838, "v": 2839, "窃": 2840, "侉": 2841, "郁": 2842, "迂": 2843, "墓": 2844, "讲": 2845, "叐": 2846, "鹬": 2847, "殆": 2848, "丸": 2849, "钦": 2850, "搂": 2851, "邯": 2852, "垭": 2853, "咆": 2854, "襄": 2855, "骸": 2856, "拟": 2857, "畜": 2858, "氟": 2859, "打": 2860, "苏": 2861, "隅": 2862, "是": 2863, "噼": 2864, "蔬": 2865, "澈": 2866, "忙": 2867, "辕": 2868, "讴": 2869, "煮": 2870, "胁": 2871, "枢": 2872, "凌": 2873, "承": 2874, "脊": 2875, "拆": 2876, "覆": 2877, "萍": 2878, "露": 2879, "转": 2880, "互": 2881, "裂": 2882, "淦": 2883, "的": 2884, "驰": 2885, "螺": 2886, "杆": 2887, "丽": 2888, "俩": 2889, "杉": 2890, "谁": 2891, "y": 2892, "置": 2893, "哀": 2894, "鼓": 2895, "等": 2896, "春": 2897, "翅": 2898, "拖": 2899, "钣": 2900, "块": 2901, "徘": 2902, "磐": 2903, "傻": 2904, "怜": 2905, "纯": 2906, "记": 2907, "刑": 2908, "倚": 2909, "豹": 2910, "栉": 2911, "想": 2912, "轩": 2913, "眶": 2914, "─": 2915, "橘": 2916, "沁": 2917, "陶": 2918, "慨": 2919, "菏": 2920, "辆": 2921, "城": 2922, "胆": 2923, "浸": 2924, "鹿": 2925, "z": 2926, "扰": 2927, "捕": 2928, "两": 2929, "憋": 2930, "赏": 2931, "抽": 2932, "拓": 2933, "阔": 2934, "辩": 2935, "館": 2936, "或": 2937, "某": 2938, "爵": 2939, "轰": 2940, "伊": 2941, "霹": 2942, "腕": 2943, "$": 2944, "府": 2945, "扭": 2946, "以": 2947, "彀": 2948, "健": 2949, "晋": 2950, "残": 2951, "娱": 2952, "妥": 2953, "鲵": 2954, "蟹": 2955, "‘": 2956, "定": 2957, "伶": 2958, "陌": 2959, "翰": 2960, "靶": 2961, "x": 2962, "磺": 2963, "选": 2964, "脏": 2965, "隆": 2966, "钱": 2967, "釜": 2968, "水": 2969, "秃": 2970, "踌": 2971, "谐": 2972, "臣": 2973, "椭": 2974, "仕": 2975, "燎": 2976, "橹": 2977, "，": 2978, "i": 2979, "宜": 2980, "稿": 2981, "孜": 2982, "凰": 2983, "嘉": 2984, "年": 2985, "炅": 2986, "揭": 2987, "遗": 2988, "确": 2989, "轿": 2990, "竞": 2991, "似": 2992, "仇": 2993, "蚂": 2994, "汽": 2995, "肿": 2996, "署": 2997, "烈": 2998, "舞": 2999, "贾": 3000, "校": 3001, "拙": 3002, "谣": 3003, "韶": 3004, "召": 3005, "阳": 3006, "珍": 3007, "能": 3008, "挣": 3009, "乃": 3010, "滥": 3011, "鲍": 3012, "钟": 3013, "但": 3014, "喂": 3015, "槽": 3016, "妃": 3017, "典": 3018, ";": 3019, "峨": 3020, "沿": 3021, "胥": 3022, "铸": 3023, "蚁": 3024, "契": 3025, "饮": 3026, "瞩": 3027, "拾": 3028, "章": 3029, "痹": 3030, "瑶": 3031, "翩": 3032, "婧": 3033, "柴": 3034, "罢": 3035, "猥": 3036, "楚": 3037, "浜": 3038, "岳": 3039, "套": 3040, "屉": 3041, "特": 3042, "k": 3043, "８": 3044, "垢": 3045, "底": 3046, "０": 3047, "轻": 3048, "尺": 3049, "腹": 3050, "拌": 3051, "遐": 3052, "距": 3053, "狙": 3054, "F": 3055, "途": 3056, "睫": 3057, "贡": 3058, "般": 3059, "组": 3060, "首": 3061, "微": 3062, "勺": 3063, "维": 3064, "稠": 3065, "朱": 3066, "涿": 3067, "迄": 3068, "矮": 3069, "立": 3070, "傀": 3071, "殃": 3072, "谷": 3073, "勇": 3074, "雄": 3075, "俨": 3076, "饱": 3077, "牡": 3078, "丛": 3079, "庄": 3080, "*": 3081, "祷": 3082, "艾": 3083, "飘": 3084, "堕": 3085, "啦": 3086, "饰": 3087, "户": 3088, "磨": 3089, "亨": 3090, "藁": 3091, "克": 3092, "孤": 3093, "缩": 3094, "跑": 3095, "莱": 3096, "樯": 3097, "叔": 3098, "株": 3099, "梓": 3100, "怀": 3101, "司": 3102, "衿": 3103, "赎": 3104, "产": 3105, "责": 3106, "笋": 3107, "床": 3108, "{": 3109, "奖": 3110, "都": 3111, "富": 3112, "昌": 3113, "禹": 3114, "哭": 3115, "尚": 3116, "权": 3117, "淫": 3118, "摧": 3119, "抔": 3120, "迪": 3121, "诉": 3122, "道": 3123, "于": 3124, "彦": 3125, "描": 3126, "·": 3127, "峰": 3128, "仿": 3129, "帜": 3130, "幸": 3131, "赫": 3132, "锡": 3133, "胸": 3134, "犹": 3135, "戒": 3136, "哇": 3137, "质": 3138, "辅": 3139, "碉": 3140, "耍": 3141, "曰": 3142, "旗": 3143, "极": 3144, "褶": 3145, "移": 3146, "奢": 3147, "桌": 3148, "飚": 3149, "：": 3150, "湿": 3151, "摘": 3152, "鹊": 3153, "啡": 3154, "悼": 3155, "紫": 3156, "崖": 3157, "韭": 3158, "迭": 3159, "弹": 3160, "碑": 3161, "伙": 3162, "踩": 3163, "祖": 3164, "臭": 3165, "囤": 3166, "杜": 3167, "望": 3168, "掰": 3169, "始": 3170, ">": 3171, "暑": 3172, "诫": 3173, "侃": 3174, "须": 3175, "连": 3176, "梏": 3177, "坏": 3178, "怕": 3179, "滕": 3180, "恺": 3181, "猴": 3182, "獎": 3183, "脐": 3184, "限": 3185, "楷": 3186, "贞": 3187, "战": 3188, "付": 3189, "鼠": 3190, "旨": 3191, "兆": 3192, "锌": 3193, "哦": 3194, "宗": 3195, "艘": 3196, "较": 3197, "嘱": 3198, "搬": 3199, "秧": 3200, "讳": 3201, "挚": 3202, "滔": 3203, "轴": 3204, "元": 3205, "甭": 3206, "咽": 3207, "傅": 3208, "×": 3209, "隔": 3210, "失": 3211, "隙": 3212, "许": 3213, "岸": 3214, "蚌": 3215, "钰": 3216, "留": 3217, "冰": 3218, "填": 3219, "經": 3220, "眼": 3221, "渣": 3222, "咖": 3223, "照": 3224, "穆": 3225, "蕉": 3226, "渔": 3227, "个": 3228, "假": 3229, "中": 3230, "锟": 3231, "阶": 3232, "沛": 3233, "胜": 3234, "篡": 3235, "腺": 3236, "单": 3237, "湛": 3238, "枪": 3239, "碧": 3240, "冲": 3241, "鹳": 3242, "獐": 3243, "驾": 3244, "《": 3245, "電": 3246, "布": 3247, "旁": 3248, "柳": 3249, "孩": 3250, "碾": 3251, "角": 3252, "崭": 3253, "撑": 3254, "荣": 3255, "迹": 3256, "狄": 3257, "」": 3258, "弯": 3259, "突": 3260, "泉": 3261, "洼": 3262, "枫": 3263, "蹊": 3264, "然": 3265, "坎": 3266, "靓": 3267, "懿": 3268, "请": 3269, "订": 3270, "蹲": 3271, "办": 3272, "嗒": 3273, "晨": 3274, "烧": 3275, "魄": 3276, "牟": 3277, "赔": 3278, "丈": 3279, "泞": 3280, "牌": 3281, "闺": 3282, "别": 3283, "潭": 3284, "喷": 3285, "珂": 3286, "侠": 3287, "丝": 3288, "雪": 3289, "气": 3290, "晰": 3291, "踞": 3292, "咱": 3293, "念": 3294, "丑": 3295, "匙": 3296, "姝": 3297, "兵": 3298, "斎": 3299, "系": 3300, "枕": 3301, "毒": 3302, "阮": 3303, "挝": 3304, "慕": 3305, "點": 3306, "吼": 3307, "赴": 3308, "①": 3309, "规": 3310, "插": 3311, "徙": 3312, "我": 3313, "操": 3314, "协": 3315, "韵": 3316, "尸": 3317, "培": 3318, "柩": 3319, "口": 3320, "迎": 3321, "缺": 3322, "续": 3323, "古": 3324, "复": 3325, "远": 3326, "点": 3327, "患": 3328, "同": 3329, "視": 3330, "X": 3331, "汇": 3332, "璐": 3333, "泣": 3334, "啧": 3335, "依": 3336, "捷": 3337, "努": 3338, "逞": 3339, "疹": 3340, "艰": 3341, "声": 3342, "蜂": 3343, "拨": 3344, "罕": 3345, "罄": 3346, "2": 3347, "!": 3348, "卷": 3349, "陲": 3350, "吡": 3351, "悉": 3352, "座": 3353, "咴": 3354, "杭": 3355, "曳": 3356, "合": 3357, "瓣": 3358, "侥": 3359, "福": 3360, "湘": 3361, "腑": 3362, "魂": 3363, "韧": 3364, "丕": 3365, "昊": 3366, "怠": 3367, "返": 3368, "盛": 3369, "貌": 3370, "桔": 3371, "外": 3372, "宣": 3373, "Ⅲ": 3374, "指": 3375, "繁": 3376, "鲤": 3377, "院": 3378, "芬": 3379, "诬": 3380, "一": 3381, "现": 3382, "所": 3383, "膜": 3384, "姜": 3385, "拐": 3386, "竣": 3387, "箕": 3388, "饿": 3389, "参": 3390, "戳": 3391, "妍": 3392, "买": 3393, "攘": 3394, "艇": 3395, "蛮": 3396, "教": 3397, "显": 3398, "冻": 3399, "臀": 3400, "/": 3401, "啉": 3402, "漏": 3403, "饶": 3404, "型": 3405, "匕": 3406, "宪": 3407, "委": 3408, "补": 3409, "呵": 3410, "供": 3411, "W": 3412, "杨": 3413, "辣": 3414, "啤": 3415, "殿": 3416, "莫": 3417, "焰": 3418, "透": 3419, "枀": 3420, "t": 3421, "猫": 3422, "取": 3423, "丰": 3424, "涂": 3425, "仆": 3426, "只": 3427, "胯": 3428, "戎": 3429, "也": 3430, "幼": 3431, "侣": 3432, "瓦": 3433, "础": 3434, "魔": 3435, "逢": 3436, "雁": 3437, "褂": 3438, "犯": 3439, "茫": 3440, "嚣": 3441, "萨": 3442, "炼": 3443, "他": 3444, "裴": 3445, "钧": 3446, "7": 3447, "鄙": 3448, "姻": 3449, "火": 3450, "占": 3451, "悴": 3452, "丢": 3453, "低": 3454, "赖": 3455, "忍": 3456, "怡": 3457, "髂": 3458, "桶": 3459, "萌": 3460, "娓": 3461, "横": 3462, "仙": 3463, "烙": 3464, "貨": 3465, "丘": 3466, "琳": 3467, "德": 3468, "(": 3469, "森": 3470, "纸": 3471, "赤": 3472, "怯": 3473, "祭": 3474, "骏": 3475, "蒜": 3476, "快": 3477, "耗": 3478, "媳": 3479, "潢": 3480, "E": 3481, "料": 3482, "度": 3483, "消": 3484, "重": 3485, "绿": 3486, "恤": 3487, "▲": 3488, "银": 3489, "齿": 3490, "畲": 3491, "赐": 3492, "济": 3493, "婉": 3494, "舆": 3495, "臼": 3496, "毙": 3497, "戬": 3498, "伟": 3499, "坑": 3500, "游": 3501, "姑": 3502, "製": 3503, "镖": 3504, "虹": 3505, "创": 3506, "断": 3507, "鞠": 3508, "其": 3509, "誉": 3510, "李": 3511, "喀": 3512, "趣": 3513, "履": 3514, "昵": 3515, "观": 3516, "遥": 3517, "使": 3518, "铃": 3519, "镜": 3520, "粮": 3521, "\"": 3522, "毁": 3523, "据": 3524, "哽": 3525, "婵": 3526, "椿": 3527, "裔": 3528, "惨": 3529, "董": 3530, "敕": 3531, "嵌": 3532, "I": 3533, "舍": 3534, "濑": 3535, "细": 3536, "毅": 3537, "浦": 3538, "桨": 3539, "那": 3540, "揣": 3541, "诡": 3542, "寞": 3543, "趁": 3544, "湄": 3545, "镍": 3546, "穿": 3547, "玲": 3548, "彩": 3549, "萧": 3550, "搁": 3551, "旱": 3552, "窒": 3553, "瓤": 3554, "桑": 3555, "蜗": 3556, "茸": 3557, "遮": 3558, "亵": 3559, "遛": 3560, "虫": 3561, "宅": 3562, "牧": 3563, "羡": 3564, "展": 3565, "鞋": 3566, "凿": 3567, "从": 3568, "号": 3569, "盟": 3570, "垒": 3571, "辄": 3572, "桎": 3573, "爸": 3574, "岑": 3575, "伏": 3576, "睽": 3577, "陋": 3578, "揠": 3579, "排": 3580, "发": 3581, "^": 3582, "杠": 3583, "屡": 3584, "稀": 3585, "嘛": 3586, "浆": 3587, "劈": 3588, "樱": 3589, "赵": 3590, "步": 3591, "朋": 3592, "览": 3593, "纤": 3594, "如": 3595, "堪": 3596, "暨": 3597, "亭": 3598, "赁": 3599, "锯": 3600, "周": 3601, "面": 3602, "霰": 3603, "鳌": 3604, "裸": 3605, "劲": 3606, "伪": 3607, "钊": 3608, "麒": 3609, "―": 3610, "槐": 3611, "毫": 3612, "亦": 3613, "侨": 3614, "朗": 3615, "榄": 3616, "悔": 3617, "雯": 3618, "５": 3619, "巍": 3620, "绰": 3621, "铜": 3622, "肖": 3623, "视": 3624, "啃": 3625, "瑛": 3626, "先": 3627, "衅": 3628, "夏": 3629, "甬": 3630, "磷": 3631, "旦": 3632, "壤": 3633, "篇": 3634, "演": 3635, "译": 3636, "史": 3637, "臆": 3638, "梧": 3639, "怦": 3640, "饺": 3641, "脆": 3642, "迚": 3643, "顺": 3644, "拮": 3645, "扁": 3646, "咕": 3647, "Ⅱ": 3648, "斱": 3649, "淄": 3650, "宙": 3651, "盯": 3652, "盈": 3653, "曾": 3654, "椎": 3655, "搀": 3656, "蛛": 3657, "侯": 3658, "欲": 3659, "缸": 3660, "扇": 3661, "挑": 3662, "汉": 3663, "考": 3664, "锅": 3665, "鸠": 3666, "癿": 3667, "危": 3668, "笺": 3669, "关": 3670, "笛": 3671, "堂": 3672, "逐": 3673, "肢": 3674, "熙": 3675, "￥": 3676, "蔽": 3677, "俭": 3678, "挺": 3679, "棍": 3680, "槛": 3681, "泗": 3682, "籁": 3683, "析": 3684, "箭": 3685, "辈": 3686, "相": 3687, "涉": 3688, "敦": 3689, "榜": 3690, "鸭": 3691, "喝": 3692, "瓮": 3693, "絮": 3694, "%": 3695, "王": 3696, "霞": 3697, "栏": 3698, "汗": 3699, "告": 3700, "唉": 3701, "效": 3702, "赶": 3703, "掀": 3704, "抿": 3705, "缇": 3706, "碳": 3707, "习": 3708, "厉": 3709, "击": 3710, "脯": 3711, "庞": 3712, "乡": 3713, "伦": 3714, "自": 3715, "淳": 3716, "阗": 3717, "诏": 3718, "矣": 3719, "徒": 3720, "s": 3721, "跟": 3722, "旋": 3723, "咙": 3724, "抑": 3725, "投": 3726, "陵": 3727, "婕": 3728, "汾": 3729, "滏": 3730, "谓": 3731, "矢": 3732, "涩": 3733, "麗": 3734, "病": 3735, "拭": 3736, "粥": 3737, "皆": 3738, "厨": 3739, "疤": 3740, "妇": 3741, "乌": 3742, "僵": 3743, "恨": 3744, "擂": 3745, "锈": 3746, "吁": 3747, "钓": 3748, "蹭": 3749, "好": 3750, "恪": 3751, "擦": 3752, "闹": 3753, "惊": 3754, "赌": 3755, "俄": 3756, "踏": 3757, "给": 3758, "慷": 3759, "蠢": 3760, "涵": 3761, "曝": 3762, "慎": 3763, "悬": 3764, "書": 3765, "殖": 3766, "廓": 3767, "睐": 3768, "凛": 3769, "喇": 3770, "陪": 3771, "冤": 3772, "砖": 3773, "醴": 3774, "窟": 3775, "隶": 3776, "赓": 3777, "被": 3778, "棵": 3779, "宽": 3780, "糠": 3781, "爪": 3782, "话": 3783, "赛": 3784, "伐": 3785, "天": 3786, "逸": 3787, "禺": 3788, "朴": 3789, "乙": 3790, "慈": 3791, "药": 3792, "闸": 3793, "荆": 3794, "电": 3795, "死": 3796, "疼": 3797, "樓": 3798, "琮": 3799, "邹": 3800, "误": 3801, "斬": 3802, "概": 3803, "梭": 3804, "纬": 3805, "眾": 3806, "猜": 3807, "瞒": 3808, "寄": 3809, "酒": 3810, "懂": 3811, "购": 3812, "咫": 3813, "赅": 3814, "颈": 3815, "倒": 3816, "虑": 3817, "爱": 3818, "炬": 3819, "乾": 3820, "态": 3821, "紊": 3822, "惠": 3823, "副": 3824, "吵": 3825, "匐": 3826, "涤": 3827, "牛": 3828, "脑": 3829, "壹": 3830, "犁": 3831, "辰": 3832, "恒": 3833, "墅": 3834, "四": 3835, "邀": 3836, "充": 3837, "恢": 3838, "淞": 3839, "琉": 3840, "苟": 3841, "崽": 3842, "海": 3843, "蕊": 3844, "国": 3845, "式": 3846, "诞": 3847, "蔑": 3848, "诲": 3849, "哗": 3850, "祛": 3851, "潇": 3852, "彼": 3853, "惜": 3854, "油": 3855, "粹": 3856, "仃": 3857, "j": 3858, "督": 3859, "楼": 3860, "衍": 3861, "拯": 3862, "袂": 3863, "住": 3864, "蓄": 3865, "震": 3866, "怒": 3867, "播": 3868, "详": 3869, "昭": 3870, "囡": 3871, "久": 3872, "防": 3873, "苔": 3874, "折": 3875, "泳": 3876, "堵": 3877, "清": 3878, "冼": 3879, "将": 3880, "封": 3881, "厦": 3882, "毂": 3883, "H": 3884, "蒙": 3885, "居": 3886, "爷": 3887, "妻": 3888, "祈": 3889, "星": 3890, "奉": 3891, "后": 3892, "殴": 3893, "澶": 3894, "8": 3895, "予": 3896, "m": 3897, "梳": 3898, "切": 3899, "提": 3900, "傍": 3901, "歉": 3902, "圈": 3903, "吴": 3904, "帐": 3905, "郝": 3906, "氯": 3907, "日": 3908, "位": 3909, "妆": 3910, "条": 3911, "担": 3912, "涧": 3913, "铤": 3914, "翼": 3915, "巩": 3916}